fcsp_api/__init__.py
fcsp_api/client.py
fcsp_api/config.py
fcsp_api/scanner.py
fcsp_api-0.1.3.dist-info/licenses/LICENSE
fcsp_api-0.1.3.dist-info/METADATA
fcsp_api-0.1.3.dist-info/WHEEL
fcsp_api-0.1.3.dist-info/entry_points.txt
fcsp_api-0.1.3.dist-info/top_level.txt
fcsp_api-0.1.3.dist-info/RECORD
