Metadata-Version: 2.4
Name: fcsp-api
Version: 0.1.3
Summary: A Python library for interacting with Ford Charge Station Pro (FCSP) devices via their REST API
Home-page: https://github.com/ericpullen/fcsp-api
Author: Eric Pullen
Author-email: Eric Pullen <eric@ericpullen.com>
License: MIT
Project-URL: Homepage, https://github.com/ericpullen/fcsp-api
Project-URL: Documentation, https://github.com/ericpullen/fcsp-api#readme
Project-URL: Repository, https://github.com/ericpullen/fcsp-api.git
Project-URL: Issues, https://github.com/ericpullen/fcsp-api/issues
Keywords: ford,charging,evse,electric-vehicle,home-automation,iot,api
Classifier: Development Status :: 4 - Beta
Classifier: Intended Audience :: Developers
Classifier: License :: OSI Approved :: MIT License
Classifier: Operating System :: OS Independent
Classifier: Programming Language :: Python :: 3
Classifier: Programming Language :: Python :: 3.8
Classifier: Programming Language :: Python :: 3.9
Classifier: Programming Language :: Python :: 3.10
Classifier: Programming Language :: Python :: 3.11
Classifier: Programming Language :: Python :: 3.12
Classifier: Topic :: Home Automation
Classifier: Topic :: Software Development :: Libraries :: Python Modules
Classifier: Topic :: Internet :: WWW/HTTP :: Dynamic Content
Classifier: Topic :: System :: Hardware
Requires-Python: >=3.8
License-File: LICENSE
Requires-Dist: requests>=2.25.0
Requires-Dist: urllib3>=1.26.0
Provides-Extra: dev
Requires-Dist: pytest>=6.0; extra == "dev"
Requires-Dist: pytest-cov>=2.0; extra == "dev"
Requires-Dist: black>=21.0; extra == "dev"
Requires-Dist: flake8>=3.8; extra == "dev"
Requires-Dist: mypy>=0.800; extra == "dev"
Requires-Dist: twine>=3.0; extra == "dev"
Requires-Dist: build>=0.10; extra == "dev"
Provides-Extra: crypto
Requires-Dist: cryptography>=3.0.0; extra == "crypto"
Dynamic: author
Dynamic: home-page
Dynamic: license-file
Dynamic: requires-python
